GenerativeProteomics/__init__.py
GenerativeProteomics/dataset.py
GenerativeProteomics/hypers.py
GenerativeProteomics/model.py
GenerativeProteomics/output.py
GenerativeProteomics/protogain.py
GenerativeProteomics/utils.py
GenerativeProteomics-0.2.1.dist-info/LICENSE
GenerativeProteomics-0.2.1.dist-info/METADATA
GenerativeProteomics-0.2.1.dist-info/WHEEL
GenerativeProteomics-0.2.1.dist-info/top_level.txt
GenerativeProteomics-0.2.1.dist-info/RECORD
