Metadata-Version: 2.1
Name: GenerativeProteomics
Version: 0.2.1
Summary: A Python package for synthetic proteomics data augmentation using ProtoGAIN
Home-page: https://github.com/QuantitativeBiology/GenerativeProteomics
Author: Diogo Ferreira, Emanuel Gonçalves, Jorge Ribeiro, Leandro Sobral, Rita Gama
Author-email: quantitative-biology@googlegroups.com
License: BSD-3-Clause
Classifier: Programming Language :: Python :: 3.10
Classifier: Programming Language :: Python :: 3.11
Classifier: License :: OSI Approved :: BSD License
Classifier: Operating System :: OS Independent
Requires-Python: >=3.10, <3.12
License-File: LICENSE
Requires-Dist: torch
Requires-Dist: torchinfo
Requires-Dist: numpy
Requires-Dist: tqdm
Requires-Dist: pandas
Requires-Dist: scikit-learn
Requires-Dist: optuna
Requires-Dist: psutil
Requires-Dist: anndata
